m3u8-stubs/METADATA.toml
m3u8-stubs/__init__.pyi
m3u8-stubs/httpclient.pyi
m3u8-stubs/mixins.pyi
m3u8-stubs/model.pyi
m3u8-stubs/parser.pyi
m3u8-stubs/protocol.pyi
m3u8-stubs/py.typed
m3u8-stubs/version_matching.pyi
m3u8-stubs/version_matching_rules.pyi
types_m3u8-6.0.0.20250625.dist-info/licenses/LICENSE
types_m3u8-6.0.0.20250625.dist-info/METADATA
types_m3u8-6.0.0.20250625.dist-info/WHEEL
types_m3u8-6.0.0.20250625.dist-info/top_level.txt
types_m3u8-6.0.0.20250625.dist-info/RECORD
